{
  "cards": [
    {
      "type": "servant",
      "set_number": 1,
      "card_number": 1,
      "name": "Ironclad Knight",
      "attack": "5",
      "defense": "7",
      "element": "earth",
      "servant_type": "warrior",
      "ability": "Shield Bash",
      "flavor": "A steadfast defender of the realm.",
      "artwork": "/images/ironclad_knight.png"
    },
    {
      "type": "servant",
      "set_number": 1,
      "card_number": 2,
      "name": "Flame Sorcerer",
      "attack": "4",
      "defense": "3",
      "element": "fire",
      "servant_type": "mage",
      "ability": "Fireball",
      "flavor": "A master of destructive flames.",
      "artwork": "/images/flame_sorcerer.png"
    },
    {
      "type": "servant",
      "set_number": 1,
      "card_number": 3,
      "name": "Shadow Assassin",
      "attack": "6",
      "defense": "2",
      "element": "darkness",
      "servant_type": "rogue",
      "ability": "Backstab",
      "flavor": "Strikes unseen from the shadows.",
      "artwork": "/images/shadow_assassin.png"
    },
    {
      "type": "servant",
      "set_number": 1,
      "card_number": 4,
      "name": "Storm Rider",
      "attack": "7",
      "defense": "4",
      "element": "thunder",
      "servant_type": "rider",
      "ability": "Lightning Charge",
      "flavor": "Rides the storm with unmatched speed.",
      "artwork": "/images/storm_rider.png"
    },
    {
      "type": "servant",
      "set_number": 1,
      "card_number": 5,
      "name": "Forest Guardian",
      "attack": "3",
      "defense": "8",
      "element": "air",
      "servant_type": "druid",
      "ability": "Nature's Shield",
      "flavor": "Protector of the ancient woods.",
      "artwork": "/images/forest_guardian.png"
    },
    {
      "type": "servant",
      "set_number": 1,
      "card_number": 6,
      "name": "Crystal Mage",
      "attack": "5",
      "defense": "5",
      "element": "light",
      "servant_type": "mage",
      "ability": "Crystal Blast",
      "flavor": "Harnesses the power of light crystals.",
      "artwork": "/images/crystal_mage.png"
    },
    {
      "type": "servant",
      "set_number": 1,
      "card_number": 7,
      "name": "Void Stalker",
      "attack": "?",
      "defense": "?",
      "element": "void",
      "servant_type": "hunter",
      "ability": "Unknown",
      "flavor": "A mysterious figure from the void.",
      "artwork": "/images/void_stalker.png"
    },
    {
      "type": "servant",
      "set_number": 1,
      "card_number": 8,
      "name": "Water Priestess",
      "attack": "3",
      "defense": "6",
      "element": "water",
      "servant_type": "cleric",
      "ability": "Healing Waters",
      "flavor": "Channels the purifying power of water.",
      "artwork": "/images/water_priestess.png"
    },
    {
      "type": "servant",
      "set_number": 1,
      "card_number": 9,
      "name": "Earthshaker",
      "attack": "8",
      "defense": "4",
      "element": "earth",
      "servant_type": "giant",
      "ability": "Seismic Slam",
      "flavor": "Brings the ground crashing down.",
      "artwork": "/images/earthshaker.png"
    },
    {
      "type": "servant",
      "set_number": 1,
      "card_number": 10,
      "name": "Thunder Hawk",
      "attack": "6",
      "defense": "5",
      "element": "thunder",
      "servant_type": "beast",
      "ability": "Storm Dive",
      "flavor": "A fierce bird commanding thunder.",
      "artwork": "/images/thunder_hawk.png"
    },
    {
      "type": "servant",
      "set_number": 1,
      "card_number": 11,
      "name": "Dark Reaper",
      "attack": "7",
      "defense": "6",
      "element": "darkness",
      "servant_type": "warrior",
      "ability": "Soul Harvest",
      "flavor": "Harvests souls with his scythe.",
      "artwork": "/images/dark_reaper.png"
    },
    {
      "type": "servant",
      "set_number": 1,
      "card_number": 12,
      "name": "Light Paladin",
      "attack": "6",
      "defense": "7",
      "element": "light",
      "servant_type": "knight",
      "ability": "Holy Strike",
      "flavor": "Fights with the power of light.",
      "artwork": "/images/light_paladin.png"
    },
    {
      "type": "servant",
      "set_number": 1,
      "card_number": 13,
      "name": "Air Ranger",
      "attack": "4",
      "defense": "4",
      "element": "air",
      "servant_type": "archer",
      "ability": "Wind Arrow",
      "flavor": "Shoots arrows carried by the wind.",
      "artwork": "/images/air_ranger.png"
    },
    {
      "type": "servant",
      "set_number": 1,
      "card_number": 14,
      "name": "Fire Drake",
      "attack": "8",
      "defense": "5",
      "element": "fire",
      "servant_type": "dragon",
      "ability": "Flame Breath",
      "flavor": "Breathes scorching fire on foes.",
      "artwork": "/images/fire_drake.png"
    },
    {
      "type": "servant",
      "set_number": 1,
      "card_number": 15,
      "name": "Water Serpent",
      "attack": "5",
      "defense": "6",
      "element": "water",
      "servant_type": "beast",
      "ability": "Tidal Wave",
      "flavor": "Controls the raging seas.",
      "artwork": "/images/water_serpent.png"
    },
    {
      "type": "servant",
      "set_number": 1,
      "card_number": 16,
      "name": "Earth Golem",
      "attack": "7",
      "defense": "9",
      "element": "earth",
      "servant_type": "construct",
      "ability": "Stone Fist",
      "flavor": "A living statue of rock and soil.",
      "artwork": "/images/earth_golem.png"
    },
    {
      "type": "servant",
      "set_number": 1,
      "card_number": 17,
      "name": "Thunder Wolf",
      "attack": "6",
      "defense": "5",
      "element": "thunder",
      "servant_type": "beast",
      "ability": "Electric Howl",
      "flavor": "A wolf charged with electric energy.",
      "artwork": "/images/thunder_wolf.png"
    },
    {
      "type": "servant",
      "set_number": 1,
      "card_number": 18,
      "name": "Dark Witch",
      "attack": "5",
      "defense": "3",
      "element": "darkness",
      "servant_type": "mage",
      "ability": "Curse",
      "flavor": "Casts dark hexes on enemies.",
      "artwork": "/images/dark_witch.png"
    },
    {
      "type": "servant",
      "set_number": 1,
      "card_number": 19,
      "name": "Light Cleric",
      "attack": "2",
      "defense": "6",
      "element": "light",
      "servant_type": "cleric",
      "ability": "Healing Light",
      "flavor": "Heals allies with holy light.",
      "artwork": "/images/light_cleric.png"
    },
    {
      "type": "servant",
      "set_number": 1,
      "card_number": 20,
      "name": "Air Elemental",
      "attack": "5",
      "defense": "5",
      "element": "air",
      "servant_type": "elemental",
      "ability": "Gale Force",
      "flavor": "Embodiment of the wind.",
      "artwork": "/images/air_elemental.png"
    },
    {
      "type": "spell",
      "set_number": 1,
      "card_number": 21,
      "name": "Fireball",
      "effect": "Deal 5 damage to all enemies.",
      "artwork": "/images/fireball.png"
    },
    {
      "type": "spell",
      "set_number": 1,
      "card_number": 22,
      "name": "Healing Rain",
      "effect": "Restore 6 life to all allies.",
      "artwork": "/images/healing_rain.png"
    },
    {
      "type": "spell",
      "set_number": 1,
      "card_number": 23,
      "name": "Lightning Bolt",
      "effect": "Deal 7 damage to one enemy.",
      "artwork": "/images/lightning_bolt.png"
    },
    {
      "type": "spell",
      "set_number": 1,
      "card_number": 24,
      "name": "Earthquake",
      "effect": "Deal 4 damage to all enemies and stun.",
      "artwork": "/images/earthquake.png"
    },
    {
      "type": "spell",
      "set_number": 1,
      "card_number": 25,
      "name": "Dark Pact",
      "effect": "Sacrifice 3 life to draw 2 cards.",
      "artwork": "/images/dark_pact.png"
    },
    {
      "type": "spell",
      "set_number": 1,
      "card_number": 26,
      "name": "Shield Wall",
      "effect": "Increase defense of all allies by 3.",
      "artwork": "/images/shield_wall.png"
    },
    {
      "type": "spell",
      "set_number": 1,
      "card_number": 27,
      "name": "Wind Gust",
      "effect": "Push all enemies back 2 spaces.",
      "artwork": "/images/wind_gust.png"
    },
    {
      "type": "spell",
      "set_number": 1,
      "card_number": 28,
      "name": "Void Surge",
      "effect": "Deal 6 damage and silence one enemy.",
      "artwork": "/images/void_surge.png"
    },
    {
      "type": "spell",
      "set_number": 1,
      "card_number": 29,
      "name": "Holy Light",
      "effect": "Restore 8 life to one ally.",
      "artwork": "/images/holy_light.png"
    },
    {
      "type": "spell",
      "set_number": 1,
      "card_number": 30,
      "name": "Frost Nova",
      "effect": "Deal 3 damage and freeze all enemies.",
      "artwork": "/images/frost_nova.png"
    },
    {
      "type": "spell",
      "set_number": 1,
      "card_number": 31,
      "name": "Arcane Explosion",
      "effect": "Deal 4 damage to all enemies.",
      "artwork": "/images/arcane_explosion.png"
    },
    {
      "type": "spell",
      "set_number": 1,
      "card_number": 32,
      "name": "Mana Drain",
      "effect": "Remove 3 mana from an enemy.",
      "artwork": "/images/mana_drain.png"
    },
    {
      "type": "spell",
      "set_number": 1,
      "card_number": 33,
      "name": "Curse of Weakness",
      "effect": "Reduce attack of one enemy by 4.",
      "artwork": "/images/curse_of_weakness.png"
    },
    {
      "type": "spell",
      "set_number": 1,
      "card_number": 34,
      "name": "Blessing of Strength",
      "effect": "Increase attack of one ally by 5.",
      "artwork": "/images/blessing_of_strength.png"
    },
    {
      "type": "spell",
      "set_number": 1,
      "card_number": 35,
      "name": "Teleport",
      "effect": "Move one ally to any position.",
      "artwork": "/images/teleport.png"
    },
    {
      "type": "avatar",
      "set_number": 1,
      "card_number": 36,
      "name": "Knight Commander",
      "life_points": 30,
      "ability": "Inspire: All servants gain +1 attack.",
      "flavor": "Leads with courage and honor.",
      "artwork": "/images/knight_commander.png"
    },
    {
      "type": "avatar",
      "set_number": 1,
      "card_number": 37,
      "name": "Archmage Supreme",
      "life_points": 25,
      "ability": "Mana Surge: Gain 2 extra mana each turn.",
      "flavor": "Master of arcane arts.",
      "artwork": "/images/archmage_supreme.png"
    },
    {
      "type": "avatar",
      "set_number": 1,
      "card_number": 38,
      "name": "Shadow Warlord",
      "life_points": 28,
      "ability": "Fear Aura: Enemies lose 1 attack.",
      "flavor": "Commands the legions of darkness.",
      "artwork": "/images/shadow_warlord.png"
    }
  ]
}
